{
  "hatoage.wata777.f5.si": {
    "type": "site",
    "status": "ok",
    "nslookup": true,
    "http": 200,
    "http_ms": 112,
    "checked_at": "2026-03-06T20:49:17Z"
  },
  "sakura.kotoca.net": {
    "type": "site",
    "status": "ok",
    "nslookup": true,
    "http": 200,
    "http_ms": 135,
    "checked_at": "2026-03-06T20:49:17Z"
  },
  "bot.sakurahp.f5.si": {
    "type": "discord_bot",
    "status": "ok",
    "raw": {
      "ok": true,
      "updatedAt": "2026/3/7 5:49:14",
      "shards": [
        {
          "shardId": 0,
          "ready": true,
          "ping": 81,
          "guilds": 0,
          "uptime": 27067633
        },
        {
          "shardId": 1,
          "ready": true,
          "ping": 94,
          "guilds": 1,
          "uptime": 27060217
        }
      ]
    }
  }
}
