{
  "hatoage.wata777.f5.si": {
    "type": "site",
    "status": "ok",
    "nslookup": true,
    "http": 200,
    "http_ms": 246,
    "checked_at": "2026-04-13T12:45:50Z"
  },
  "sakura.kotoca.net": {
    "type": "site",
    "status": "ok",
    "nslookup": true,
    "http": 200,
    "http_ms": 73,
    "checked_at": "2026-04-13T12:45:50Z"
  },
  "bot.sakurahp.f5.si": {
    "type": "discord_bot",
    "status": "ok",
    "raw": {
      "ok": true,
      "updatedAt": "2026/4/13 21:45:18",
      "shards": [
        {
          "shardId": 0,
          "ready": true,
          "ping": 80,
          "guilds": 1,
          "uptime": 10626595
        },
        {
          "shardId": 1,
          "ready": true,
          "ping": 78,
          "guilds": 2,
          "uptime": 10620207
        }
      ]
    }
  }
}
