{
  "hatoage.wata777.f5.si": {
    "type": "site",
    "status": "ok",
    "nslookup": true,
    "http": 200,
    "http_ms": 155,
    "checked_at": "2026-03-29T17:28:22Z"
  },
  "sakura.kotoca.net": {
    "type": "site",
    "status": "ok",
    "nslookup": true,
    "http": 200,
    "http_ms": 47,
    "checked_at": "2026-03-29T17:28:22Z"
  },
  "bot.sakurahp.f5.si": {
    "type": "discord_bot",
    "status": "ok",
    "raw": {
      "ok": true,
      "updatedAt": "2026/3/30 2:28:09",
      "shards": [
        {
          "shardId": 0,
          "ready": true,
          "ping": 81,
          "guilds": 1,
          "uptime": 94448379
        },
        {
          "shardId": 1,
          "ready": true,
          "ping": 90,
          "guilds": 2,
          "uptime": 94441305
        }
      ]
    }
  }
}
