{
  "hatoage.wata777.f5.si": {
    "type": "site",
    "status": "ok",
    "nslookup": true,
    "http": 200,
    "http_ms": 292,
    "checked_at": "2026-03-16T10:15:52Z"
  },
  "sakura.kotoca.net": {
    "type": "site",
    "status": "ok",
    "nslookup": true,
    "http": 200,
    "http_ms": 97,
    "checked_at": "2026-03-16T10:15:53Z"
  },
  "bot.sakurahp.f5.si": {
    "type": "discord_bot",
    "status": "ok",
    "raw": {
      "ok": true,
      "updatedAt": "2026/3/16 19:15:27",
      "shards": [
        {
          "shardId": 0,
          "ready": true,
          "ping": 81,
          "guilds": 2,
          "uptime": 82328335
        },
        {
          "shardId": 1,
          "ready": true,
          "ping": 91,
          "guilds": 1,
          "uptime": 82322404
        }
      ]
    }
  }
}
