{
  "hatoage.wata777.f5.si": {
    "type": "site",
    "status": "ok",
    "nslookup": true,
    "http": 200,
    "http_ms": 228,
    "checked_at": "2026-01-21T09:58:25Z"
  },
  "sakura.kotoca.net": {
    "type": "site",
    "status": "ok",
    "nslookup": true,
    "http": 200,
    "http_ms": 46,
    "checked_at": "2026-01-21T09:58:25Z"
  },
  "bot.sakurahp.f5.si": {
    "type": "discord_bot",
    "status": "ok",
    "raw": {
      "ok": true,
      "updatedAt": "2026/1/21 18:57:58",
      "shards": [
        {
          "shardId": 0,
          "ready": true,
          "ping": 89,
          "guilds": 0,
          "uptime": 156631373
        },
        {
          "shardId": 1,
          "ready": true,
          "ping": 88,
          "guilds": 1,
          "uptime": 44972260
        }
      ]
    }
  }
}
