{
  "hatoage.wata777.f5.si": {
    "type": "site",
    "status": "ok",
    "nslookup": true,
    "http": 200,
    "http_ms": 158,
    "checked_at": "2026-03-01T17:10:43Z"
  },
  "sakura.kotoca.net": {
    "type": "site",
    "status": "ok",
    "nslookup": true,
    "http": 200,
    "http_ms": 50,
    "checked_at": "2026-03-01T17:10:43Z"
  },
  "bot.sakurahp.f5.si": {
    "type": "discord_bot",
    "status": "ok",
    "raw": {
      "ok": true,
      "updatedAt": "2026/3/2 2:10:30",
      "shards": [
        {
          "shardId": 0,
          "ready": true,
          "ping": 88,
          "guilds": 0,
          "uptime": 569656105
        },
        {
          "shardId": 1,
          "ready": true,
          "ping": 90,
          "guilds": 1,
          "uptime": 569649476
        }
      ]
    }
  }
}
