{
  "hatoage.wata777.f5.si": {
    "type": "site",
    "status": "ok",
    "nslookup": true,
    "http": 200,
    "http_ms": 271,
    "checked_at": "2026-05-13T10:43:52Z"
  },
  "sakura.kotoca.net": {
    "type": "site",
    "status": "ok",
    "nslookup": true,
    "http": 200,
    "http_ms": 38,
    "checked_at": "2026-05-13T10:43:52Z"
  },
  "bot.sakurahp.f5.si": {
    "type": "discord_bot",
    "status": "ok",
    "raw": {
      "ok": true,
      "updatedAt": "2026/5/13 19:43:23",
      "shards": [
        {
          "shardId": 0,
          "ready": true,
          "ping": 92,
          "guilds": 1,
          "uptime": 1118305054
        },
        {
          "shardId": 1,
          "ready": true,
          "ping": 79,
          "guilds": 2,
          "uptime": 1118298642
        }
      ]
    }
  }
}
