{
  "hatoage.wata777.f5.si": {
    "type": "site",
    "status": "ok",
    "nslookup": true,
    "http": 200,
    "http_ms": 103,
    "checked_at": "2026-01-18T21:58:36Z"
  },
  "sakura.kotoca.net": {
    "type": "site",
    "status": "ok",
    "nslookup": true,
    "http": 200,
    "http_ms": 35,
    "checked_at": "2026-01-18T21:58:36Z"
  },
  "bot.sakurahp.f5.si": {
    "type": "discord_bot",
    "status": "ok",
    "raw": {
      "ok": true,
      "updatedAt": "2026/1/19 6:57:54",
      "shards": [
        {
          "shardId": 0,
          "ready": true,
          "ping": 88,
          "guilds": 0,
          "uptime": 2248782
        },
        {
          "shardId": 1,
          "ready": true,
          "ping": 90,
          "guilds": 1,
          "uptime": 37777286
        }
      ]
    }
  }
}
