{
  "hatoage.wata777.f5.si": {
    "type": "site",
    "status": "ok",
    "nslookup": true,
    "http": 200,
    "http_ms": 152,
    "checked_at": "2026-01-11T17:09:15Z"
  },
  "sakura.kotoca.net": {
    "type": "site",
    "status": "ok",
    "nslookup": true,
    "http": 200,
    "http_ms": 80,
    "checked_at": "2026-01-11T17:09:16Z"
  },
  "bot.sakurahp.f5.si": {
    "type": "discord_bot",
    "status": "ok",
    "raw": {
      "ok": true,
      "updatedAt": "2026/1/12 2:08:17",
      "shards": [
        {
          "shardId": 0,
          "ready": true,
          "ping": 87,
          "guilds": 0,
          "uptime": 25253003
        },
        {
          "shardId": 1,
          "ready": true,
          "ping": 92,
          "guilds": 1,
          "uptime": 25527431
        }
      ]
    }
  }
}
