{
  "hatoage.wata777.f5.si": {
    "type": "site",
    "status": "ok",
    "nslookup": true,
    "http": 200,
    "http_ms": 250,
    "checked_at": "2026-02-03T22:01:04Z"
  },
  "sakura.kotoca.net": {
    "type": "site",
    "status": "ok",
    "nslookup": true,
    "http": 200,
    "http_ms": 101,
    "checked_at": "2026-02-03T22:01:04Z"
  },
  "bot.sakurahp.f5.si": {
    "type": "discord_bot",
    "status": "ok",
    "raw": {
      "ok": true,
      "updatedAt": "2026/2/4 7:00:22",
      "shards": [
        {
          "shardId": 0,
          "ready": true,
          "ping": 81,
          "guilds": 0,
          "uptime": 240911898
        },
        {
          "shardId": 1,
          "ready": true,
          "ping": 85,
          "guilds": 1,
          "uptime": 240904252
        }
      ]
    }
  }
}
