{
  "hatoage.wata777.f5.si": {
    "type": "site",
    "status": "ok",
    "nslookup": true,
    "http": 200,
    "http_ms": 149,
    "checked_at": "2026-04-06T21:47:06Z"
  },
  "sakura.kotoca.net": {
    "type": "site",
    "status": "ok",
    "nslookup": true,
    "http": 200,
    "http_ms": 48,
    "checked_at": "2026-04-06T21:47:06Z"
  },
  "bot.sakurahp.f5.si": {
    "type": "discord_bot",
    "status": "ok",
    "raw": {
      "ok": true,
      "updatedAt": "2026/4/7 6:46:32",
      "shards": [
        {
          "shardId": 0,
          "ready": true,
          "ping": 79,
          "guilds": 1,
          "uptime": 167289613
        },
        {
          "shardId": 1,
          "ready": true,
          "ping": 79,
          "guilds": 2,
          "uptime": 167283350
        }
      ]
    }
  }
}
