{
  "hatoage.wata777.f5.si": {
    "type": "site",
    "status": "ok",
    "nslookup": true,
    "http": 200,
    "http_ms": 315,
    "checked_at": "2026-01-01T09:56:46Z"
  },
  "sakura.kotoca.net": {
    "type": "site",
    "status": "ok",
    "nslookup": true,
    "http": 200,
    "http_ms": 22,
    "checked_at": "2026-01-01T09:56:46Z"
  },
  "bot.sakurahp.f5.si": {
    "type": "discord_bot",
    "status": "ok",
    "raw": {
      "ok": true,
      "updatedAt": "2026/1/1 18:56:40",
      "shards": [
        {
          "shardId": 0,
          "ready": true,
          "ping": 94,
          "guilds": 0,
          "uptime": 1436195
        },
        {
          "shardId": 1,
          "ready": true,
          "ping": 92,
          "guilds": 1,
          "uptime": 7560107
        }
      ]
    }
  }
}
