{
  "hatoage.wata777.f5.si": {
    "type": "site",
    "status": "ok",
    "nslookup": true,
    "http": 200,
    "http_ms": 167,
    "checked_at": "2026-02-07T19:03:31Z"
  },
  "sakura.kotoca.net": {
    "type": "site",
    "status": "ok",
    "nslookup": true,
    "http": 200,
    "http_ms": 121,
    "checked_at": "2026-02-07T19:03:31Z"
  },
  "bot.sakurahp.f5.si": {
    "type": "discord_bot",
    "status": "ok",
    "raw": {
      "ok": true,
      "updatedAt": "2026/2/8 4:02:55",
      "shards": [
        {
          "shardId": 0,
          "ready": true,
          "ping": 102,
          "guilds": 0,
          "uptime": 38048321
        },
        {
          "shardId": 1,
          "ready": true,
          "ping": 91,
          "guilds": 1,
          "uptime": 38040708
        }
      ]
    }
  }
}
