{
  "hatoage.wata777.f5.si": {
    "type": "site",
    "status": "ok",
    "nslookup": true,
    "http": 200,
    "http_ms": 133,
    "checked_at": "2026-04-12T01:10:09Z"
  },
  "sakura.kotoca.net": {
    "type": "site",
    "status": "ok",
    "nslookup": true,
    "http": 200,
    "http_ms": 60,
    "checked_at": "2026-04-12T01:10:09Z"
  },
  "bot.sakurahp.f5.si": {
    "type": "discord_bot",
    "status": "ok",
    "raw": {
      "ok": true,
      "updatedAt": "2026/4/12 10:09:40",
      "shards": [
        {
          "shardId": 0,
          "ready": true,
          "ping": 79,
          "guilds": 1,
          "uptime": 611477376
        },
        {
          "shardId": 1,
          "ready": true,
          "ping": 79,
          "guilds": 2,
          "uptime": 611471113
        }
      ]
    }
  }
}
