{
  "hatoage.wata777.f5.si": {
    "type": "site",
    "status": "ok",
    "nslookup": true,
    "http": 200,
    "http_ms": 106,
    "checked_at": "2025-12-25T11:44:06Z"
  },
  "sakura.kotoca.net": {
    "type": "site",
    "status": "ok",
    "nslookup": true,
    "http": 200,
    "http_ms": 129,
    "checked_at": "2025-12-25T11:44:06Z"
  },
  "bot.sakurahp.f5.si": {
    "type": "discord_bot",
    "status": "ok",
    "raw": {"ok":true,"updatedAt":"57953/4/29 4:07:10","shards":[{"shardId":0,"ready":true,"ping":92,"guilds":0,"uptime":97571637},{"shardId":1,"ready":true,"ping":92,"guilds":1,"uptime":8293279}]}
  }
}
