{
  "hatoage.wata777.f5.si": {
    "type": "site",
    "status": "ok",
    "nslookup": true,
    "http": 200,
    "http_ms": 344,
    "checked_at": "2026-01-26T21:37:18Z"
  },
  "sakura.kotoca.net": {
    "type": "site",
    "status": "ok",
    "nslookup": true,
    "http": 200,
    "http_ms": 68,
    "checked_at": "2026-01-26T21:37:18Z"
  },
  "bot.sakurahp.f5.si": {
    "type": "discord_bot",
    "status": "ok",
    "raw": {
      "ok": true,
      "updatedAt": "2026/1/27 6:36:50",
      "shards": [
        {
          "shardId": 0,
          "ready": true,
          "ping": 88,
          "guilds": 0,
          "uptime": 44345095
        },
        {
          "shardId": 1,
          "ready": true,
          "ping": 90,
          "guilds": 1,
          "uptime": 250684278
        }
      ]
    }
  }
}
