{
  "hatoage.wata777.f5.si": {
    "type": "site",
    "status": "ok",
    "nslookup": true,
    "http": 200,
    "http_ms": 111,
    "checked_at": "2026-01-10T17:44:35Z"
  },
  "sakura.kotoca.net": {
    "type": "site",
    "status": "ok",
    "nslookup": true,
    "http": 200,
    "http_ms": 62,
    "checked_at": "2026-01-10T17:44:35Z"
  },
  "bot.sakurahp.f5.si": {
    "type": "discord_bot",
    "status": "ok",
    "raw": {
      "ok": true,
      "updatedAt": "2026/1/11 2:43:52",
      "shards": [
        {
          "shardId": 0,
          "ready": true,
          "ping": 90,
          "guilds": 0,
          "uptime": 41607967
        },
        {
          "shardId": 1,
          "ready": true,
          "ping": 91,
          "guilds": 1,
          "uptime": 54781689
        }
      ]
    }
  }
}
